cez_distribution_hdo/__init__.py
cez_distribution_hdo/__version__.py
cez_distribution_hdo/client.py
cez_distribution_hdo/const.py
cez_distribution_hdo/exceptions.py
cez_distribution_hdo/models.py
cez_distribution_hdo/service.py
cez_distribution_hdo/tariffs.py
cez_distribution_hdo/validators.py
cez_distribution_hdo-0.3.0.dist-info/METADATA
cez_distribution_hdo-0.3.0.dist-info/WHEEL
cez_distribution_hdo-0.3.0.dist-info/licenses/LICENSE
cez_distribution_hdo-0.3.0.dist-info/RECORD
