Metadata-Version: 2.4
Name: cez-distribution-hdo
Version: 0.3.0
Summary: Python library for reading and interpreting CEZ Distribution HDO (NT/VT) switch schedules.
Project-URL: Repository, https://github.com/pokornyIt/cez-distribution-hdo
Project-URL: Issues, https://github.com/pokornyIt/cez-distribution-hdo/issues
Project-URL: Releases, https://github.com/pokornyIt/cez-distribution-hdo/releases
Author-email: pokornyIt <8665714+pokornyIt@users.noreply.github.com>
License-Expression: MIT
License-File: LICENSE
Keywords: cez,hdo,home-assistant,nt,tariff,vt
Classifier: Intended Audience :: Developers
Classifier: License :: OSI Approved :: MIT License
Classifier: Operating System :: OS Independent
Classifier: Programming Language :: Python :: 3 :: Only
Classifier: Programming Language :: Python :: 3.13
Requires-Python: >=3.13
Requires-Dist: httpx~=0.28.0
